CHANGELOG.md
LICENSE
MANIFEST.in
README.md
requirements.in
setup.cfg
setup.py
bin/xmm
config/example.servers.json
config/example.sources.json
config/xmm.ini
config/xmm.logging.ini
docs/Makefile
docs/api.rst
docs/conf.py
docs/configuration.rst
docs/developers.rst
docs/index.rst
docs/installation.rst
docs/intro.rst
docs/license.rst
docs/tests.rst
docs/upgrading.rst
docs/usage.rst
docs/_static/xmm.gif
pkg/xmm.bash
pkg/xmm.zsh
resources/data/maps.json
resources/data/maps.json.shasums
resources/data/maps.json.zip
resources/data/xmm-asciicast.json
resources/images/xmm.gif
xmm/__about__.py
xmm/__init__.py
xmm/base.py
xmm/cli.py
xmm/config.py
xmm/exceptions.py
xmm/library.py
xmm/logger.py
xmm/map.py
xmm/repository.py
xmm/server.py
xmm/store.py
xmm/util.py
xmm.egg-info/PKG-INFO
xmm.egg-info/SOURCES.txt
xmm.egg-info/dependency_links.txt
xmm.egg-info/entry_points.txt
xmm.egg-info/requires.txt
xmm.egg-info/top_level.txt
xmm/plugins/__init__.py
xmm/plugins/pluginbase.py
xmm/plugins/pluginloader.py
xmm/plugins/hello/__init__.py