Metadata-Version: 1.1
Name: xmm
Version: 0.8.0
Summary: A package manager for Xonotic.
Home-page: https://www.github.com/z/xonotic-map-manager
Author: Tyler Mulligan
Author-email: z@xnz.me
License: MIT
Keywords: xonotic,xonotic-servers,xonotic-maps,gaming,cli
Platform: UNKNOWN
Classifier: Intended Audience :: End Users/Desktop
Classifier: Intended Audience :: System Administrators
Classifier: License :: OSI Approved :: MIT License
Classifier: Development Status :: 5 - Production/Stable
Classifier: Environment :: Console
Classifier: Topic :: Games/Entertainment
Classifier: Topic :: System :: Archiving :: Packaging
Classifier: Programming Language :: Python :: 3
Classifier: Programming Language :: Python :: 3.4
Classifier: Programming Language :: Python :: 3.5
